omspy/NorenRestApi-0.0.30-py2.py3-none-any.whl
omspy/__init__.py
omspy/algos/README.md
omspy/algos/__init__.py
omspy/algos/straddle.py
omspy/algos/trailing.py
omspy/base.py
omspy/brokers/__init__.py
omspy/brokers/api_helper.py
omspy/brokers/finvasia.py
omspy/brokers/finvasia.yaml
omspy/brokers/icici.py
omspy/brokers/icici.yaml
omspy/brokers/neo.py
omspy/brokers/neo.yaml
omspy/brokers/noren.py
omspy/brokers/noren.yaml
omspy/brokers/paper.py
omspy/brokers/paper.yaml
omspy/brokers/zerodha.py
omspy/brokers/zerodha.yaml
omspy/models.py
omspy/multi.py
omspy/order.py
omspy/orders/__init__.py
omspy/orders/depth.py
omspy/orders/peg.py
omspy/orders/stop.py
omspy/simulation/__init__.py
omspy/simulation/models.py
omspy/simulation/server.py
omspy/simulation/virtual.py
omspy/utils.py
omspy-0.20.0.dist-info/LICENSE
omspy-0.20.0.dist-info/METADATA
omspy-0.20.0.dist-info/WHEEL
omspy-0.20.0.dist-info/RECORD
