Metadata-Version: 2.3
Name: omspy
Version: 0.20.0
Summary: 
License: MIT
Author: Ubermensch
Author-email: uberdeveloper001@gmail.com
Requires-Python: >=3.11,<4.0
Classifier: License :: OSI Approved :: MIT License
Classifier: Programming Language :: Python :: 3
Classifier: Programming Language :: Python :: 3.11
Classifier: Programming Language :: Python :: 3.12
Classifier: Programming Language :: Python :: 3.13
Requires-Dist: PyYAML (>=6.0.0,<7.0.0)
Requires-Dist: mkdocs-autorefs (>=1.4.2,<2.0.0)
Requires-Dist: pendulum[test] (>=3.0.0,<4.0.0)
Requires-Dist: pydantic (>=2.0.0,<3.0.0)
Requires-Dist: pyotp (>=2.9.0,<3.0.0)
Requires-Dist: sqlite-utils (>=3.22.1,<4.0.0)
Project-URL: Repository, https://github.com/uberdeveloper/omspy
